mass_manager/__init__.py
mass_manager/mass_manager.py
mass_manager/models.py
mass_manager/util/__init__.py
mass_manager/util/directories.py
mass_manager/util/singleton.py
mass_manager/util/util.py
mass_manager-0.0.9.dist-info/LICENSE
mass_manager-0.0.9.dist-info/METADATA
mass_manager-0.0.9.dist-info/WHEEL
mass_manager-0.0.9.dist-info/top_level.txt
mass_manager-0.0.9.dist-info/zip-safe
mass_manager-0.0.9.dist-info/RECORD
